HTML/Auto.py
HTML/__init__.py
HTML_Auto-0.0.5.dist-info/METADATA
HTML_Auto-0.0.5.dist-info/WHEEL
HTML_Auto-0.0.5.dist-info/top_level.txt
HTML_Auto-0.0.5.dist-info/RECORD
