Metadata-Version: 2.1
Name: HTML-Auto
Version: 0.0.5
Summary: Just another HTML tag generator (for Python)
Home-page: https://github.com/jeffa/HTML-Auto-python
Author: Jeff Anderson
Author-email: jeffa@cpan.org
License: Artistic
Platform: UNKNOWN
Classifier: Topic :: Text Processing :: Markup :: HTML
Classifier: Development Status :: 1 - Planning
Classifier: Intended Audience :: Developers
Classifier: Programming Language :: Python
Classifier: Programming Language :: Python :: 3
Classifier: Operating System :: OS Independent
Classifier: License :: OSI Approved :: Artistic License
